{
  "packs_root": "E:\\SAS\\ShadowsAndShurikens\\DevTools\\bpgen_snippets\\packs",
  "total_packs_scanned": 53,
  "total_snippets_scanned": 138,
  "total_engine_functions": 112,
  "duplicate_engine_functions": 15,
  "coverage": {
    "/Script/Engine.GameplayStatics:BeginDeferredActorSpawnFromClass": [
      {
        "pack_name": "actor_spawning_basics",
        "snippet_name": "SpawnActor_Simple",
        "bpgen_function_name": "BPGen_SpawnActor_Simple",
        "job_file": "actor_spawning_basics\\jobs\\SpawnActor_Simple_Job.json",
        "graphspec_file": "actor_spawning_basics\\graphspecs\\SpawnActor_Simple_GraphSpec.json"
      }
    ],
    "/Script/Engine.Actor:K2_DestroyActor": [
      {
        "pack_name": "actor_spawning_basics",
        "snippet_name": "DestroyActor_Simple",
        "bpgen_function_name": "BPGen_DestroyActor_Simple",
        "job_file": "actor_spawning_basics\\jobs\\DestroyActor_Simple_Job.json",
        "graphspec_file": "actor_spawning_basics\\graphspecs\\DestroyActor_Simple_GraphSpec.json"
      }
    ],
    "/Script/Engine.SkeletalMeshComponent:PlayAnimation": [
      {
        "pack_name": "animation_basics",
        "snippet_name": "Anim_PlayAnimation_OnSkeletalMesh",
        "bpgen_function_name": "BPGen_Anim_PlayAnimation_OnSkeletalMesh",
        "job_file": "animation_basics\\jobs\\Anim_PlayAnimation_OnSkeletalMesh_Job.json",
        "graphspec_file": "animation_basics\\graphspecs\\Anim_PlayAnimation_OnSkeletalMesh_GraphSpec.json"
      }
    ],
    "/Script/Engine.SkeletalMeshComponent:Stop": [
      {
        "pack_name": "animation_basics",
        "snippet_name": "Anim_Stop_OnSkeletalMesh",
        "bpgen_function_name": "BPGen_Anim_Stop_OnSkeletalMesh",
        "job_file": "animation_basics\\jobs\\Anim_Stop_OnSkeletalMesh_Job.json",
        "graphspec_file": "animation_basics\\graphspecs\\Anim_Stop_OnSkeletalMesh_GraphSpec.json"
      }
    ],
    "/Script/Engine.AnimInstance:Montage_Play": [
      {
        "pack_name": "animation_basics",
        "snippet_name": "Anim_MontagePlay_OnAnimInstance",
        "bpgen_function_name": "BPGen_Anim_MontagePlay_OnAnimInstance",
        "job_file": "animation_basics\\jobs\\Anim_MontagePlay_OnAnimInstance_Job.json",
        "graphspec_file": "animation_basics\\graphspecs\\Anim_MontagePlay_OnAnimInstance_GraphSpec.json"
      }
    ],
    "/Script/Engine.KismetArrayLibrary:Array_Add": [
      {
        "pack_name": "array_basics",
        "snippet_name": "IntArray_AddAndLength",
        "bpgen_function_name": "BPGen_Array_AddLen",
        "job_file": "array_basics\\jobs\\IntArray_AddAndLength_Job.json",
        "graphspec_file": "array_basics\\graphspecs\\IntArray_AddAndLength_GraphSpec.json"
      }
    ],
    "/Script/Engine.KismetSystemLibrary:PrintString": [
      {
        "pack_name": "array_basics",
        "snippet_name": "IntArray_ForEach_Print",
        "bpgen_function_name": "BPGen_Array_ForEachPrint",
        "job_file": "array_basics\\jobs\\IntArray_ForEach_Print_Job.json",
        "graphspec_file": "array_basics\\graphspecs\\IntArray_ForEach_Print_GraphSpec.json"
      },
      {
        "pack_name": "common_basics",
        "snippet_name": "PrintString_HelloWorld",
        "bpgen_function_name": "BPGen_HelloWorld",
        "job_file": "common_basics\\jobs\\PrintString_HelloWorld_Job.json",
        "graphspec_file": "common_basics\\graphspecs\\PrintString_HelloWorld_GraphSpec.json"
      },
      {
        "pack_name": "common_basics",
        "snippet_name": "Branch_Boilerplate",
        "bpgen_function_name": "BPGen_BranchBoilerplate",
        "job_file": "common_basics\\jobs\\Branch_Boilerplate_Job.json",
        "graphspec_file": "common_basics\\graphspecs\\Branch_Boilerplate_GraphSpec.json"
      },
      {
        "pack_name": "debug_basics",
        "snippet_name": "Debug_PrintScreenLog",
        "bpgen_function_name": "BPGen_Debug_PrintScreenLog",
        "job_file": "debug_basics\\jobs\\Debug_PrintScreenLog_Job.json",
        "graphspec_file": "debug_basics\\graphspecs\\Debug_PrintScreenLog_GraphSpec.json"
      },
      {
        "pack_name": "event_basics",
        "snippet_name": "CustomEvent_Simple",
        "bpgen_function_name": "BPGen_CustomEvent_Simple",
        "job_file": "event_basics\\jobs\\CustomEvent_Simple_Job.json",
        "graphspec_file": "event_basics\\graphspecs\\CustomEvent_Simple_GraphSpec.json"
      },
      {
        "pack_name": "flow_advanced",
        "snippet_name": "Flow_DoOnceWithReset",
        "bpgen_function_name": "BPGen_Flow_DoOnceWithReset",
        "job_file": "flow_advanced\\jobs\\Flow_DoOnceWithReset_Job.json",
        "graphspec_file": "flow_advanced\\graphspecs\\Flow_DoOnceWithReset_GraphSpec.json"
      },
      {
        "pack_name": "flow_advanced",
        "snippet_name": "Flow_Gate_OpenClose",
        "bpgen_function_name": "BPGen_Flow_Gate_OpenClose",
        "job_file": "flow_advanced\\jobs\\Flow_Gate_OpenClose_Job.json",
        "graphspec_file": "flow_advanced\\graphspecs\\Flow_Gate_OpenClose_GraphSpec.json"
      },
      {
        "pack_name": "flow_advanced",
        "snippet_name": "Flow_MultiGate_Triple",
        "bpgen_function_name": "BPGen_Flow_MultiGate_Triple",
        "job_file": "flow_advanced\\jobs\\Flow_MultiGate_Triple_Job.json",
        "graphspec_file": "flow_advanced\\graphspecs\\Flow_MultiGate_Triple_GraphSpec.json"
      },
      {
        "pack_name": "flow_basics",
        "snippet_name": "Branch_BoolInput",
        "bpgen_function_name": "BPGen_Flow_Branch",
        "job_file": "flow_basics\\jobs\\Branch_BoolInput_Job.json",
        "graphspec_file": "flow_basics\\graphspecs\\Branch_BoolInput_GraphSpec.json"
      },
      {
        "pack_name": "flow_basics",
        "snippet_name": "ForLoop_Basic",
        "bpgen_function_name": "BPGen_Flow_ForLoop",
        "job_file": "flow_basics\\jobs\\ForLoop_Basic_Job.json",
        "graphspec_file": "flow_basics\\graphspecs\\ForLoop_Basic_GraphSpec.json"
      },
      {
        "pack_name": "flow_basics",
        "snippet_name": "Sequence_Triple",
        "bpgen_function_name": "BPGen_Flow_Sequence",
        "job_file": "flow_basics\\jobs\\Sequence_Triple_Job.json",
        "graphspec_file": "flow_basics\\graphspecs\\Sequence_Triple_GraphSpec.json"
      }
    ],
    "/Script/Engine.KismetArrayLibrary:Array_Clear": [
      {
        "pack_name": "array_basics",
        "snippet_name": "IntArray_Clear",
        "bpgen_function_name": "BPGen_Array_Clear",
        "job_file": "array_basics\\jobs\\IntArray_Clear_Job.json",
        "graphspec_file": "array_basics\\graphspecs\\IntArray_Clear_GraphSpec.json"
      }
    ],
    "/Script/Engine.GameplayStatics:PlaySoundAtLocation": [
      {
        "pack_name": "audio_basics",
        "snippet_name": "Audio_PlaySoundAtLocation",
        "bpgen_function_name": "BPGen_Audio_PlaySoundAtLocation",
        "job_file": "audio_basics\\jobs\\Audio_PlaySoundAtLocation_Job.json",
        "graphspec_file": "audio_basics\\graphspecs\\Audio_PlaySoundAtLocation_GraphSpec.json"
      }
    ],
    "/Script/Engine.GameplayStatics:PlaySound2D": [
      {
        "pack_name": "audio_basics",
        "snippet_name": "Audio_PlaySound2D",
        "bpgen_function_name": "BPGen_Audio_PlaySound2D",
        "job_file": "audio_basics\\jobs\\Audio_PlaySound2D_Job.json",
        "graphspec_file": "audio_basics\\graphspecs\\Audio_PlaySound2D_GraphSpec.json"
      }
    ],
    "/Script/Engine.AudioComponent:SetVolumeMultiplier": [
      {
        "pack_name": "audio_basics",
        "snippet_name": "Audio_SetVolume_OnComponent",
        "bpgen_function_name": "BPGen_Audio_SetVolume_OnComponent",
        "job_file": "audio_basics\\jobs\\Audio_SetVolume_OnComponent_Job.json",
        "graphspec_file": "audio_basics\\graphspecs\\Audio_SetVolume_OnComponent_GraphSpec.json"
      }
    ],
    "/Script/Engine.KismetMathLibrary:BooleanAND": [
      {
        "pack_name": "bool_logic_basics",
        "snippet_name": "Bool_AndOr",
        "bpgen_function_name": "BPGen_Bool_AndOr",
        "job_file": "bool_logic_basics\\jobs\\Bool_AndOr_Job.json",
        "graphspec_file": "bool_logic_basics\\graphspecs\\Bool_AndOr_GraphSpec.json"
      },
      {
        "pack_name": "bool_logic_basics",
        "snippet_name": "Branch_ComplexCondition",
        "bpgen_function_name": "BPGen_Branch_ComplexCondition",
        "job_file": "bool_logic_basics\\jobs\\Branch_ComplexCondition_Job.json",
        "graphspec_file": "bool_logic_basics\\graphspecs\\Branch_ComplexCondition_GraphSpec.json"
      }
    ],
    "/Script/Engine.KismetMathLibrary:Not_PreBool": [
      {
        "pack_name": "bool_logic_basics",
        "snippet_name": "Bool_Not",
        "bpgen_function_name": "BPGen_Bool_Not",
        "job_file": "bool_logic_basics\\jobs\\Bool_Not_Job.json",
        "graphspec_file": "bool_logic_basics\\graphspecs\\Bool_Not_GraphSpec.json"
      }
    ],
    "/Script/Engine.PlayerController:SetViewTargetWithBlend": [
      {
        "pack_name": "camera_basics",
        "snippet_name": "Camera_SetViewTargetWithBlend",
        "bpgen_function_name": "BPGen_Camera_SetViewTargetWithBlend",
        "job_file": "camera_basics\\jobs\\Camera_SetViewTargetWithBlend_Job.json",
        "graphspec_file": "camera_basics\\graphspecs\\Camera_SetViewTargetWithBlend_GraphSpec.json"
      }
    ],
    "/Script/Engine.CameraComponent:SetFieldOfView": [
      {
        "pack_name": "camera_basics",
        "snippet_name": "Camera_SetFieldOfView",
        "bpgen_function_name": "BPGen_Camera_SetFieldOfView",
        "job_file": "camera_basics\\jobs\\Camera_SetFieldOfView_Job.json",
        "graphspec_file": "camera_basics\\graphspecs\\Camera_SetFieldOfView_GraphSpec.json"
      }
    ],
    "/Script/Engine.SpringArmComponent:SetEnableCameraLag": [
      {
        "pack_name": "camera_basics",
        "snippet_name": "CameraArm_SetLagSettings",
        "bpgen_function_name": "BPGen_CameraArm_SetLagSettings",
        "job_file": "camera_basics\\jobs\\CameraArm_SetLagSettings_Job.json",
        "graphspec_file": "camera_basics\\graphspecs\\CameraArm_SetLagSettings_GraphSpec.json"
      }
    ],
    "/Script/Engine.GameplayStatics:GetPlayerCameraManager": [
      {
        "pack_name": "camera_view_basics",
        "snippet_name": "Camera_GetPlayerCameraManager",
        "bpgen_function_name": "BPGen_Camera_GetPlayerCameraManager",
        "job_file": "camera_view_basics\\jobs\\Camera_GetPlayerCameraManager_Job.json",
        "graphspec_file": "camera_view_basics\\graphspecs\\Camera_GetPlayerCameraManager_GraphSpec.json"
      }
    ],
    "/Script/Engine.Actor:GetActorEyesViewPoint": [
      {
        "pack_name": "camera_view_basics",
        "snippet_name": "Camera_GetActorEyesViewPoint",
        "bpgen_function_name": "BPGen_Camera_GetActorEyesViewPoint",
        "job_file": "camera_view_basics\\jobs\\Camera_GetActorEyesViewPoint_Job.json",
        "graphspec_file": "camera_view_basics\\graphspecs\\Camera_GetActorEyesViewPoint_GraphSpec.json"
      }
    ],
    "/Script/Engine.GameplayStatics:SetViewTargetWithBlend": [
      {
        "pack_name": "camera_view_basics",
        "snippet_name": "Camera_SetViewTargetWithBlend",
        "bpgen_function_name": "BPGen_Camera_SetViewTargetWithBlend",
        "job_file": "camera_view_basics\\jobs\\Camera_SetViewTargetWithBlend_Job.json",
        "graphspec_file": "camera_view_basics\\graphspecs\\Camera_SetViewTargetWithBlend_GraphSpec.json"
      }
    ],
    "/Script/Engine.PrimitiveComponent:SetCollisionEnabled": [
      {
        "pack_name": "collision_basics",
        "snippet_name": "Collision_SetEnabled",
        "bpgen_function_name": "BPGen_Collision_SetEnabled",
        "job_file": "collision_basics\\jobs\\Collision_SetEnabled_Job.json",
        "graphspec_file": "collision_basics\\graphspecs\\Collision_SetEnabled_GraphSpec.json"
      }
    ],
    "/Script/Engine.PrimitiveComponent:SetCollisionResponseToChannel": [
      {
        "pack_name": "collision_basics",
        "snippet_name": "Collision_SetResponseToChannel",
        "bpgen_function_name": "BPGen_Collision_SetResponseToChannel",
        "job_file": "collision_basics\\jobs\\Collision_SetResponseToChannel_Job.json",
        "graphspec_file": "collision_basics\\graphspecs\\Collision_SetResponseToChannel_GraphSpec.json"
      }
    ],
    "/Script/Engine.KismetSystemLibrary:LineTraceSingle": [
      {
        "pack_name": "common_basics",
        "snippet_name": "SimpleTrace_LineTraceSingle",
        "bpgen_function_name": "BPGen_SimpleTrace",
        "job_file": "common_basics\\jobs\\SimpleTrace_LineTraceSingle_Job.json",
        "graphspec_file": "common_basics\\graphspecs\\SimpleTrace_LineTraceSingle_GraphSpec.json"
      },
      {
        "pack_name": "trace_advanced",
        "snippet_name": "LineTrace_ByChannel_Advanced",
        "bpgen_function_name": "BPGen_Trace_LineTraceAdv",
        "job_file": "trace_advanced\\jobs\\LineTrace_ByChannel_Advanced_Job.json",
        "graphspec_file": "trace_advanced\\graphspecs\\LineTrace_ByChannel_Advanced_GraphSpec.json"
      },
      {
        "pack_name": "trace_basics",
        "snippet_name": "Trace_LineSingle",
        "bpgen_function_name": "BPGen_Trace_LineSingle",
        "job_file": "trace_basics\\jobs\\Trace_LineSingle_Job.json",
        "graphspec_file": "trace_basics\\graphspecs\\Trace_LineSingle_GraphSpec.json"
      },
      {
        "pack_name": "trace_line_channel_basics",
        "snippet_name": "Trace_LineSingle",
        "bpgen_function_name": "BPGen_Trace_LineSingle",
        "job_file": "trace_line_channel_basics\\jobs\\Trace_LineSingle_Job.json",
        "graphspec_file": "trace_line_channel_basics\\graphspecs\\Trace_LineSingle_GraphSpec.json"
      }
    ],
    "/Script/Engine.Actor:GetOwner": [
      {
        "pack_name": "component_basics",
        "snippet_name": "Actor_GetOwner",
        "bpgen_function_name": "BPGen_Actor_GetOwner",
        "job_file": "component_basics\\jobs\\Actor_GetOwner_Job.json",
        "graphspec_file": "component_basics\\graphspecs\\Actor_GetOwner_GraphSpec.json"
      }
    ],
    "/Script/Engine.Actor:GetComponentByClass": [
      {
        "pack_name": "component_basics",
        "snippet_name": "Actor_GetComponentByClass",
        "bpgen_function_name": "BPGen_Actor_GetComponentByClass",
        "job_file": "component_basics\\jobs\\Actor_GetComponentByClass_Job.json",
        "graphspec_file": "component_basics\\graphspecs\\Actor_GetComponentByClass_GraphSpec.json"
      }
    ],
    "/Script/Engine.SceneComponent:GetWorldLocation": [
      {
        "pack_name": "component_basics",
        "snippet_name": "SceneComponent_GetWorldLocation",
        "bpgen_function_name": "BPGen_SceneComponent_GetWorldLocation",
        "job_file": "component_basics\\jobs\\SceneComponent_GetWorldLocation_Job.json",
        "graphspec_file": "component_basics\\graphspecs\\SceneComponent_GetWorldLocation_GraphSpec.json"
      }
    ],
    "/Script/Engine.SceneComponent:GetForwardVector": [
      {
        "pack_name": "component_directions_basics",
        "snippet_name": "Component_GetForwardVector",
        "bpgen_function_name": "BPGen_Component_GetForwardVector",
        "job_file": "component_directions_basics\\jobs\\Component_GetForwardVector_Job.json",
        "graphspec_file": "component_directions_basics\\graphspecs\\Component_GetForwardVector_GraphSpec.json"
      }
    ],
    "/Script/Engine.SceneComponent:GetRightVector": [
      {
        "pack_name": "component_directions_basics",
        "snippet_name": "Component_GetRightVector",
        "bpgen_function_name": "BPGen_Component_GetRightVector",
        "job_file": "component_directions_basics\\jobs\\Component_GetRightVector_Job.json",
        "graphspec_file": "component_directions_basics\\graphspecs\\Component_GetRightVector_GraphSpec.json"
      }
    ],
    "/Script/Engine.SceneComponent:GetUpVector": [
      {
        "pack_name": "component_directions_basics",
        "snippet_name": "Component_GetUpVector",
        "bpgen_function_name": "BPGen_Component_GetUpVector",
        "job_file": "component_directions_basics\\jobs\\Component_GetUpVector_Job.json",
        "graphspec_file": "component_directions_basics\\graphspecs\\Component_GetUpVector_GraphSpec.json"
      }
    ],
    "/Script/Engine.SceneComponent:SetWorldLocation": [
      {
        "pack_name": "component_transform_basics",
        "snippet_name": "Comp_SetWorldLocation",
        "bpgen_function_name": "BPGen_Comp_SetWorldLocation",
        "job_file": "component_transform_basics\\jobs\\Comp_SetWorldLocation_Job.json",
        "graphspec_file": "component_transform_basics\\graphspecs\\Comp_SetWorldLocation_GraphSpec.json"
      }
    ],
    "/Script/Engine.SceneComponent:SetWorldRotation": [
      {
        "pack_name": "component_transform_basics",
        "snippet_name": "Comp_SetWorldRotation",
        "bpgen_function_name": "BPGen_Comp_SetWorldRotation",
        "job_file": "component_transform_basics\\jobs\\Comp_SetWorldRotation_Job.json",
        "graphspec_file": "component_transform_basics\\graphspecs\\Comp_SetWorldRotation_GraphSpec.json"
      }
    ],
    "/Script/Engine.SceneComponent:AddWorldOffset": [
      {
        "pack_name": "component_transform_basics",
        "snippet_name": "Comp_AddWorldOffset",
        "bpgen_function_name": "BPGen_Comp_AddWorldOffset",
        "job_file": "component_transform_basics\\jobs\\Comp_AddWorldOffset_Job.json",
        "graphspec_file": "component_transform_basics\\graphspecs\\Comp_AddWorldOffset_GraphSpec.json"
      }
    ],
    "/Script/Engine.Controller:GetPawn": [
      {
        "pack_name": "controller_basics",
        "snippet_name": "Controller_GetControlledPawn",
        "bpgen_function_name": "BPGen_Controller_GetControlledPawn",
        "job_file": "controller_basics\\jobs\\Controller_GetControlledPawn_Job.json",
        "graphspec_file": "controller_basics\\graphspecs\\Controller_GetControlledPawn_GraphSpec.json"
      }
    ],
    "/Script/Engine.Controller:Possess": [
      {
        "pack_name": "controller_basics",
        "snippet_name": "Controller_PossessPawn",
        "bpgen_function_name": "BPGen_Controller_PossessPawn",
        "job_file": "controller_basics\\jobs\\Controller_PossessPawn_Job.json",
        "graphspec_file": "controller_basics\\graphspecs\\Controller_PossessPawn_GraphSpec.json"
      }
    ],
    "/Script/Engine.Controller:UnPossess": [
      {
        "pack_name": "controller_basics",
        "snippet_name": "Controller_UnPossessPawn",
        "bpgen_function_name": "BPGen_Controller_UnPossessPawn",
        "job_file": "controller_basics\\jobs\\Controller_UnPossessPawn_Job.json",
        "graphspec_file": "controller_basics\\graphspecs\\Controller_UnPossessPawn_GraphSpec.json"
      }
    ],
    "/Script/Engine.CurveFloat:GetFloatValue": [
      {
        "pack_name": "curve_basics",
        "snippet_name": "CurveFloat_Eval",
        "bpgen_function_name": "BPGen_CurveFloat_Eval",
        "job_file": "curve_basics\\jobs\\CurveFloat_Eval_Job.json",
        "graphspec_file": "curve_basics\\graphspecs\\CurveFloat_Eval_GraphSpec.json"
      },
      {
        "pack_name": "curve_eval_basics",
        "snippet_name": "CurveFloat_GetValue",
        "bpgen_function_name": "BPGen_CurveFloat_GetValue",
        "job_file": "curve_eval_basics\\jobs\\CurveFloat_GetValue_Job.json",
        "graphspec_file": "curve_eval_basics\\graphspecs\\CurveFloat_GetValue_GraphSpec.json"
      }
    ],
    "/Script/Engine.CurveVector:GetVectorValue": [
      {
        "pack_name": "curve_basics",
        "snippet_name": "CurveVector_Eval",
        "bpgen_function_name": "BPGen_CurveVector_Eval",
        "job_file": "curve_basics\\jobs\\CurveVector_Eval_Job.json",
        "graphspec_file": "curve_basics\\graphspecs\\CurveVector_Eval_GraphSpec.json"
      },
      {
        "pack_name": "curve_eval_basics",
        "snippet_name": "CurveVector_GetValue",
        "bpgen_function_name": "BPGen_CurveVector_GetValue",
        "job_file": "curve_eval_basics\\jobs\\CurveVector_GetValue_Job.json",
        "graphspec_file": "curve_eval_basics\\graphspecs\\CurveVector_GetValue_GraphSpec.json"
      }
    ],
    "/Script/Engine.CurveLinearColor:GetLinearColorValue": [
      {
        "pack_name": "curve_eval_basics",
        "snippet_name": "CurveLinearColor_GetValue",
        "bpgen_function_name": "BPGen_CurveLinearColor_GetValue",
        "job_file": "curve_eval_basics\\jobs\\CurveLinearColor_GetValue_Job.json",
        "graphspec_file": "curve_eval_basics\\graphspecs\\CurveLinearColor_GetValue_GraphSpec.json"
      }
    ],
    "/Script/Engine.KismetDataTableLibrary:GetDataTableRow": [
      {
        "pack_name": "datatable_query_basics",
        "snippet_name": "DataTable_GetRow",
        "bpgen_function_name": "BPGen_DataTable_GetRow",
        "job_file": "datatable_query_basics\\jobs\\DataTable_GetRow_Job.json",
        "graphspec_file": "datatable_query_basics\\graphspecs\\DataTable_GetRow_GraphSpec.json"
      },
      {
        "pack_name": "datatable_query_basics",
        "snippet_name": "DataTable_RowExists",
        "bpgen_function_name": "BPGen_DataTable_RowExists",
        "job_file": "datatable_query_basics\\jobs\\DataTable_RowExists_Job.json",
        "graphspec_file": "datatable_query_basics\\graphspecs\\DataTable_RowExists_GraphSpec.json"
      }
    ],
    "/Script/Engine.KismetDataTableLibrary:GetDataTableRowNames": [
      {
        "pack_name": "datatable_query_basics",
        "snippet_name": "DataTable_GetRowNames",
        "bpgen_function_name": "BPGen_DataTable_GetRowNames",
        "job_file": "datatable_query_basics\\jobs\\DataTable_GetRowNames_Job.json",
        "graphspec_file": "datatable_query_basics\\graphspecs\\DataTable_GetRowNames_GraphSpec.json"
      }
    ],
    "/Script/Engine.KismetSystemLibrary:DrawDebugSphere": [
      {
        "pack_name": "debug_basics",
        "snippet_name": "Debug_DrawSphere",
        "bpgen_function_name": "BPGen_Debug_DrawSphere",
        "job_file": "debug_basics\\jobs\\Debug_DrawSphere_Job.json",
        "graphspec_file": "debug_basics\\graphspecs\\Debug_DrawSphere_GraphSpec.json"
      }
    ],
    "/Script/Engine.KismetSystemLibrary:DrawDebugLine": [
      {
        "pack_name": "debug_basics",
        "snippet_name": "Debug_DrawLine",
        "bpgen_function_name": "BPGen_Debug_DrawLine",
        "job_file": "debug_basics\\jobs\\Debug_DrawLine_Job.json",
        "graphspec_file": "debug_basics\\graphspecs\\Debug_DrawLine_GraphSpec.json"
      }
    ],
    "/Script/Engine.Actor:ProcessEvent": [
      {
        "pack_name": "event_basics",
        "snippet_name": "Dispatcher_BindAndBroadcast",
        "bpgen_function_name": "BPGen_Dispatcher_BindAndBroadcast",
        "job_file": "event_basics\\jobs\\Dispatcher_BindAndBroadcast_Job.json",
        "graphspec_file": "event_basics\\graphspecs\\Dispatcher_BindAndBroadcast_GraphSpec.json"
      }
    ],
    "/Script/Engine.GameplayStatics:GetPlayerCharacter": [
      {
        "pack_name": "gameplaystatics_basics",
        "snippet_name": "GS_GetPlayerCharacter",
        "bpgen_function_name": "BPGen_GS_GetPlayerCharacter",
        "job_file": "gameplaystatics_basics\\jobs\\GS_GetPlayerCharacter_Job.json",
        "graphspec_file": "gameplaystatics_basics\\graphspecs\\GS_GetPlayerCharacter_GraphSpec.json"
      }
    ],
    "/Script/Engine.GameplayStatics:GetPlayerController": [
      {
        "pack_name": "gameplaystatics_basics",
        "snippet_name": "GS_GetPlayerController",
        "bpgen_function_name": "BPGen_GS_GetPlayerController",
        "job_file": "gameplaystatics_basics\\jobs\\GS_GetPlayerController_Job.json",
        "graphspec_file": "gameplaystatics_basics\\graphspecs\\GS_GetPlayerController_GraphSpec.json"
      }
    ],
    "/Script/Engine.GameplayStatics:GetAllActorsOfClass": [
      {
        "pack_name": "gameplaystatics_basics",
        "snippet_name": "GS_GetAllActorsOfClass",
        "bpgen_function_name": "BPGen_GS_GetAllActorsOfClass",
        "job_file": "gameplaystatics_basics\\jobs\\GS_GetAllActorsOfClass_Job.json",
        "graphspec_file": "gameplaystatics_basics\\graphspecs\\GS_GetAllActorsOfClass_GraphSpec.json"
      }
    ],
    "/Script/Engine.KismetMathLibrary:Multiply_FloatFloat": [
      {
        "pack_name": "input_basics",
        "snippet_name": "Input_ScaleAxis",
        "bpgen_function_name": "BPGen_Input_ScaleAxis",
        "job_file": "input_basics\\jobs\\Input_ScaleAxis_Job.json",
        "graphspec_file": "input_basics\\graphspecs\\Input_ScaleAxis_GraphSpec.json"
      },
      {
        "pack_name": "math_basics",
        "snippet_name": "Float_MultiplyDivide",
        "bpgen_function_name": "BPGen_Math_FloatMulDiv",
        "job_file": "math_basics\\jobs\\Float_MultiplyDivide_Job.json",
        "graphspec_file": "math_basics\\graphspecs\\Float_MultiplyDivide_GraphSpec.json"
      }
    ],
    "/Script/Engine.KismetMathLibrary:SelectBool": [
      {
        "pack_name": "input_basics",
        "snippet_name": "Input_ActionToBool",
        "bpgen_function_name": "BPGen_Input_ActionToBool",
        "job_file": "input_basics\\jobs\\Input_ActionToBool_Job.json",
        "graphspec_file": "input_basics\\graphspecs\\Input_ActionToBool_GraphSpec.json"
      }
    ],
    "/Script/Engine.PlayerController:WasInputKeyJustPressed": [
      {
        "pack_name": "input_key_query_basics",
        "snippet_name": "Input_WasKeyJustPressed",
        "bpgen_function_name": "BPGen_Input_WasKeyJustPressed",
        "job_file": "input_key_query_basics\\jobs\\Input_WasKeyJustPressed_Job.json",
        "graphspec_file": "input_key_query_basics\\graphspecs\\Input_WasKeyJustPressed_GraphSpec.json"
      }
    ],
    "/Script/Engine.PlayerController:WasInputKeyJustReleased": [
      {
        "pack_name": "input_key_query_basics",
        "snippet_name": "Input_WasKeyJustReleased",
        "bpgen_function_name": "BPGen_Input_WasKeyJustReleased",
        "job_file": "input_key_query_basics\\jobs\\Input_WasKeyJustReleased_Job.json",
        "graphspec_file": "input_key_query_basics\\graphspecs\\Input_WasKeyJustReleased_GraphSpec.json"
      }
    ],
    "/Script/Engine.PlayerController:IsInputKeyDown": [
      {
        "pack_name": "input_key_query_basics",
        "snippet_name": "Input_IsInputKeyDown",
        "bpgen_function_name": "BPGen_Input_IsInputKeyDown",
        "job_file": "input_key_query_basics\\jobs\\Input_IsInputKeyDown_Job.json",
        "graphspec_file": "input_key_query_basics\\graphspecs\\Input_IsInputKeyDown_GraphSpec.json"
      }
    ],
    "/Script/Engine.KismetMathLibrary:FInterpTo": [
      {
        "pack_name": "interp_basics",
        "snippet_name": "Float_FInterpTo",
        "bpgen_function_name": "BPGen_Float_FInterpTo",
        "job_file": "interp_basics\\jobs\\Float_FInterpTo_Job.json",
        "graphspec_file": "interp_basics\\graphspecs\\Float_FInterpTo_GraphSpec.json"
      },
      {
        "pack_name": "interp_helpers_basics",
        "snippet_name": "Interp_FInterpTo",
        "bpgen_function_name": "BPGen_Interp_FInterpTo",
        "job_file": "interp_helpers_basics\\jobs\\Interp_FInterpTo_Job.json",
        "graphspec_file": "interp_helpers_basics\\graphspecs\\Interp_FInterpTo_GraphSpec.json"
      }
    ],
    "/Script/Engine.KismetMathLibrary:VInterpTo": [
      {
        "pack_name": "interp_basics",
        "snippet_name": "Vector_VInterpTo",
        "bpgen_function_name": "BPGen_Vector_VInterpTo",
        "job_file": "interp_basics\\jobs\\Vector_VInterpTo_Job.json",
        "graphspec_file": "interp_basics\\graphspecs\\Vector_VInterpTo_GraphSpec.json"
      },
      {
        "pack_name": "interp_helpers_basics",
        "snippet_name": "Interp_VInterpTo",
        "bpgen_function_name": "BPGen_Interp_VInterpTo",
        "job_file": "interp_helpers_basics\\jobs\\Interp_VInterpTo_Job.json",
        "graphspec_file": "interp_helpers_basics\\graphspecs\\Interp_VInterpTo_GraphSpec.json"
      }
    ],
    "/Script/Engine.KismetMathLibrary:Ease": [
      {
        "pack_name": "interp_basics",
        "snippet_name": "Float_EaseInOut",
        "bpgen_function_name": "BPGen_Float_EaseInOut",
        "job_file": "interp_basics\\jobs\\Float_EaseInOut_Job.json",
        "graphspec_file": "interp_basics\\graphspecs\\Float_EaseInOut_GraphSpec.json"
      }
    ],
    "/Script/Engine.KismetMathLibrary:RInterpTo": [
      {
        "pack_name": "interp_helpers_basics",
        "snippet_name": "Interp_RInterpTo",
        "bpgen_function_name": "BPGen_Interp_RInterpTo",
        "job_file": "interp_helpers_basics\\jobs\\Interp_RInterpTo_Job.json",
        "graphspec_file": "interp_helpers_basics\\graphspecs\\Interp_RInterpTo_GraphSpec.json"
      },
      {
        "pack_name": "rotator_basics",
        "snippet_name": "Rotator_RInterpTo",
        "bpgen_function_name": "BPGen_Rotator_RInterpTo",
        "job_file": "rotator_basics\\jobs\\Rotator_RInterpTo_Job.json",
        "graphspec_file": "rotator_basics\\graphspecs\\Rotator_RInterpTo_GraphSpec.json"
      }
    ],
    "/Script/Engine.GameplayStatics:OpenLevel": [
      {
        "pack_name": "level_flow_basics",
        "snippet_name": "Level_OpenLevel_Simple",
        "bpgen_function_name": "BPGen_Level_OpenLevel_Simple",
        "job_file": "level_flow_basics\\jobs\\Level_OpenLevel_Simple_Job.json",
        "graphspec_file": "level_flow_basics\\graphspecs\\Level_OpenLevel_Simple_GraphSpec.json"
      }
    ],
    "/Script/Engine.GameplayStatics:GetCurrentLevelName": [
      {
        "pack_name": "level_flow_basics",
        "snippet_name": "Level_GetCurrentLevelName",
        "bpgen_function_name": "BPGen_Level_GetCurrentLevelName",
        "job_file": "level_flow_basics\\jobs\\Level_GetCurrentLevelName_Job.json",
        "graphspec_file": "level_flow_basics\\graphspecs\\Level_GetCurrentLevelName_GraphSpec.json"
      }
    ],
    "/Script/Engine.GameplayStatics:QuitGame": [
      {
        "pack_name": "level_flow_basics",
        "snippet_name": "Level_QuitGame_Simple",
        "bpgen_function_name": "BPGen_Level_QuitGame_Simple",
        "job_file": "level_flow_basics\\jobs\\Level_QuitGame_Simple_Job.json",
        "graphspec_file": "level_flow_basics\\graphspecs\\Level_QuitGame_Simple_GraphSpec.json"
      }
    ],
    "/Script/Engine.PrimitiveComponent:SetScalarParameterValueOnMaterials": [
      {
        "pack_name": "material_basics",
        "snippet_name": "Material_SetScalarParameterOnComponent",
        "bpgen_function_name": "BPGen_Material_SetScalarParameterOnComponent",
        "job_file": "material_basics\\jobs\\Material_SetScalarParameterOnComponent_Job.json",
        "graphspec_file": "material_basics\\graphspecs\\Material_SetScalarParameterOnComponent_GraphSpec.json"
      }
    ],
    "/Script/Engine.PrimitiveComponent:SetVectorParameterValueOnMaterials": [
      {
        "pack_name": "material_basics",
        "snippet_name": "Material_SetVectorParameterOnComponent",
        "bpgen_function_name": "BPGen_Material_SetVectorParameterOnComponent",
        "job_file": "material_basics\\jobs\\Material_SetVectorParameterOnComponent_Job.json",
        "graphspec_file": "material_basics\\graphspecs\\Material_SetVectorParameterOnComponent_GraphSpec.json"
      }
    ],
    "/Script/Engine.PrimitiveComponent:CreateDynamicMaterialInstance": [
      {
        "pack_name": "material_basics",
        "snippet_name": "Material_CreateDynamicInstanceOnComponent",
        "bpgen_function_name": "BPGen_Material_CreateDynamicInstanceOnComponent",
        "job_file": "material_basics\\jobs\\Material_CreateDynamicInstanceOnComponent_Job.json",
        "graphspec_file": "material_basics\\graphspecs\\Material_CreateDynamicInstanceOnComponent_GraphSpec.json"
      }
    ],
    "/Script/Engine.KismetMathLibrary:FClamp": [
      {
        "pack_name": "math_advanced",
        "snippet_name": "Float_Clamp",
        "bpgen_function_name": "BPGen_Float_Clamp",
        "job_file": "math_advanced\\jobs\\Float_Clamp_Job.json",
        "graphspec_file": "math_advanced\\graphspecs\\Float_Clamp_GraphSpec.json"
      }
    ],
    "/Script/Engine.KismetMathLibrary:MapRangeClamped": [
      {
        "pack_name": "math_advanced",
        "snippet_name": "Float_MapRangeClamped",
        "bpgen_function_name": "BPGen_Float_MapRangeClamped",
        "job_file": "math_advanced\\jobs\\Float_MapRangeClamped_Job.json",
        "graphspec_file": "math_advanced\\graphspecs\\Float_MapRangeClamped_GraphSpec.json"
      }
    ],
    "/Script/Engine.KismetMathLibrary:Lerp": [
      {
        "pack_name": "math_advanced",
        "snippet_name": "Float_Lerp",
        "bpgen_function_name": "BPGen_Float_Lerp",
        "job_file": "math_advanced\\jobs\\Float_Lerp_Job.json",
        "graphspec_file": "math_advanced\\graphspecs\\Float_Lerp_GraphSpec.json"
      }
    ],
    "/Script/Engine.KismetMathLibrary:Add_FloatFloat": [
      {
        "pack_name": "math_basics",
        "snippet_name": "Float_AddSubtract",
        "bpgen_function_name": "BPGen_Math_FloatAddSub",
        "job_file": "math_basics\\jobs\\Float_AddSubtract_Job.json",
        "graphspec_file": "math_basics\\graphspecs\\Float_AddSubtract_GraphSpec.json"
      }
    ],
    "/Script/Engine.KismetMathLibrary:Add_VectorVector": [
      {
        "pack_name": "math_basics",
        "snippet_name": "Vector_AddDot",
        "bpgen_function_name": "BPGen_Math_VectorAddDot",
        "job_file": "math_basics\\jobs\\Vector_AddDot_Job.json",
        "graphspec_file": "math_basics\\graphspecs\\Vector_AddDot_GraphSpec.json"
      }
    ],
    "/Script/Engine.KismetMathLibrary:Sin": [
      {
        "pack_name": "math_trig_basics",
        "snippet_name": "Trig_Sin",
        "bpgen_function_name": "BPGen_Trig_Sin",
        "job_file": "math_trig_basics\\jobs\\Trig_Sin_Job.json",
        "graphspec_file": "math_trig_basics\\graphspecs\\Trig_Sin_GraphSpec.json"
      }
    ],
    "/Script/Engine.KismetMathLibrary:Cos": [
      {
        "pack_name": "math_trig_basics",
        "snippet_name": "Trig_Cos",
        "bpgen_function_name": "BPGen_Trig_Cos",
        "job_file": "math_trig_basics\\jobs\\Trig_Cos_Job.json",
        "graphspec_file": "math_trig_basics\\graphspecs\\Trig_Cos_GraphSpec.json"
      }
    ],
    "/Script/Engine.KismetMathLibrary:Atan2": [
      {
        "pack_name": "math_trig_basics",
        "snippet_name": "Trig_Atan2",
        "bpgen_function_name": "BPGen_Trig_Atan2",
        "job_file": "math_trig_basics\\jobs\\Trig_Atan2_Job.json",
        "graphspec_file": "math_trig_basics\\graphspecs\\Trig_Atan2_GraphSpec.json"
      }
    ],
    "/Script/Engine.Pawn:AddMovementInput": [
      {
        "pack_name": "movement_input_basics",
        "snippet_name": "Movement_AddMovementInput",
        "bpgen_function_name": "BPGen_Movement_AddMovementInput",
        "job_file": "movement_input_basics\\jobs\\Movement_AddMovementInput_Job.json",
        "graphspec_file": "movement_input_basics\\graphspecs\\Movement_AddMovementInput_GraphSpec.json"
      }
    ],
    "/Script/Engine.Pawn:AddControllerYawInput": [
      {
        "pack_name": "movement_input_basics",
        "snippet_name": "Movement_AddControllerYawInput",
        "bpgen_function_name": "BPGen_Movement_AddControllerYawInput",
        "job_file": "movement_input_basics\\jobs\\Movement_AddControllerYawInput_Job.json",
        "graphspec_file": "movement_input_basics\\graphspecs\\Movement_AddControllerYawInput_GraphSpec.json"
      }
    ],
    "/Script/Engine.Pawn:AddControllerPitchInput": [
      {
        "pack_name": "movement_input_basics",
        "snippet_name": "Movement_AddControllerPitchInput",
        "bpgen_function_name": "BPGen_Movement_AddControllerPitchInput",
        "job_file": "movement_input_basics\\jobs\\Movement_AddControllerPitchInput_Job.json",
        "graphspec_file": "movement_input_basics\\graphspecs\\Movement_AddControllerPitchInput_GraphSpec.json"
      }
    ],
    "/Script/Engine.NavigationSystemV1:K2_ProjectPointToNavigation": [
      {
        "pack_name": "navmesh_query_basics",
        "snippet_name": "Navmesh_ProjectPointToNavigation",
        "bpgen_function_name": "BPGen_Navmesh_ProjectPointToNavigation",
        "job_file": "navmesh_query_basics\\jobs\\Navmesh_ProjectPointToNavigation_Job.json",
        "graphspec_file": "navmesh_query_basics\\graphspecs\\Navmesh_ProjectPointToNavigation_GraphSpec.json"
      }
    ],
    "/Script/Engine.NavigationSystemV1:K2_GetRandomPointInNavigableRadius": [
      {
        "pack_name": "navmesh_query_basics",
        "snippet_name": "Navmesh_GetRandomPointInRadius",
        "bpgen_function_name": "BPGen_Navmesh_GetRandomPointInRadius",
        "job_file": "navmesh_query_basics\\jobs\\Navmesh_GetRandomPointInRadius_Job.json",
        "graphspec_file": "navmesh_query_basics\\graphspecs\\Navmesh_GetRandomPointInRadius_GraphSpec.json"
      }
    ],
    "/Script/Engine.NavigationSystemV1:K2_GetRandomReachablePointInRadius": [
      {
        "pack_name": "navmesh_query_basics",
        "snippet_name": "Navmesh_GetRandomReachablePointInRadius",
        "bpgen_function_name": "BPGen_Navmesh_GetRandomReachablePointInRadius",
        "job_file": "navmesh_query_basics\\jobs\\Navmesh_GetRandomReachablePointInRadius_Job.json",
        "graphspec_file": "navmesh_query_basics\\graphspecs\\Navmesh_GetRandomReachablePointInRadius_GraphSpec.json"
      }
    ],
    "/Script/Niagara.NiagaraFunctionLibrary:SpawnSystemAtLocation": [
      {
        "pack_name": "niagara_basics",
        "snippet_name": "Niagara_SpawnSystemAtLocation",
        "bpgen_function_name": "BPGen_Niagara_SpawnSystemAtLocation",
        "job_file": "niagara_basics\\jobs\\Niagara_SpawnSystemAtLocation_Job.json",
        "graphspec_file": "niagara_basics\\graphspecs\\Niagara_SpawnSystemAtLocation_GraphSpec.json"
      }
    ],
    "/Script/Niagara.NiagaraFunctionLibrary:SpawnSystemAttached": [
      {
        "pack_name": "niagara_basics",
        "snippet_name": "Niagara_SpawnSystemAttached",
        "bpgen_function_name": "BPGen_Niagara_SpawnSystemAttached",
        "job_file": "niagara_basics\\jobs\\Niagara_SpawnSystemAttached_Job.json",
        "graphspec_file": "niagara_basics\\graphspecs\\Niagara_SpawnSystemAttached_GraphSpec.json"
      }
    ],
    "/Script/Niagara.NiagaraComponent:SetFloatParameter": [
      {
        "pack_name": "niagara_basics",
        "snippet_name": "Niagara_SetFloatParameter",
        "bpgen_function_name": "BPGen_Niagara_SetFloatParameter",
        "job_file": "niagara_basics\\jobs\\Niagara_SetFloatParameter_Job.json",
        "graphspec_file": "niagara_basics\\graphspecs\\Niagara_SetFloatParameter_GraphSpec.json"
      }
    ],
    "/Script/Engine.PrimitiveComponent:AddImpulse": [
      {
        "pack_name": "physics_impulse_basics",
        "snippet_name": "Physics_AddImpulse",
        "bpgen_function_name": "BPGen_Physics_AddImpulse",
        "job_file": "physics_impulse_basics\\jobs\\Physics_AddImpulse_Job.json",
        "graphspec_file": "physics_impulse_basics\\graphspecs\\Physics_AddImpulse_GraphSpec.json"
      }
    ],
    "/Script/Engine.PrimitiveComponent:AddForce": [
      {
        "pack_name": "physics_impulse_basics",
        "snippet_name": "Physics_AddForce",
        "bpgen_function_name": "BPGen_Physics_AddForce",
        "job_file": "physics_impulse_basics\\jobs\\Physics_AddForce_Job.json",
        "graphspec_file": "physics_impulse_basics\\graphspecs\\Physics_AddForce_GraphSpec.json"
      }
    ],
    "/Script/Engine.PrimitiveComponent:SetSimulatePhysics": [
      {
        "pack_name": "physics_impulse_basics",
        "snippet_name": "Physics_SetSimulatePhysics",
        "bpgen_function_name": "BPGen_Physics_SetSimulatePhysics",
        "job_file": "physics_impulse_basics\\jobs\\Physics_SetSimulatePhysics_Job.json",
        "graphspec_file": "physics_impulse_basics\\graphspecs\\Physics_SetSimulatePhysics_GraphSpec.json"
      }
    ],
    "/Script/Engine.KismetMathLibrary:RandomFloatInRange": [
      {
        "pack_name": "random_basics",
        "snippet_name": "Random_FloatInRange",
        "bpgen_function_name": "BPGen_Random_FloatInRange",
        "job_file": "random_basics\\jobs\\Random_FloatInRange_Job.json",
        "graphspec_file": "random_basics\\graphspecs\\Random_FloatInRange_GraphSpec.json"
      }
    ],
    "/Script/Engine.KismetMathLibrary:RandomIntegerInRange": [
      {
        "pack_name": "random_basics",
        "snippet_name": "Random_IntInRange",
        "bpgen_function_name": "BPGen_Random_IntInRange",
        "job_file": "random_basics\\jobs\\Random_IntInRange_Job.json",
        "graphspec_file": "random_basics\\graphspecs\\Random_IntInRange_GraphSpec.json"
      }
    ],
    "/Script/Engine.KismetMathLibrary:RandomUnitVector": [
      {
        "pack_name": "random_basics",
        "snippet_name": "Random_UnitVector",
        "bpgen_function_name": "BPGen_Random_UnitVector",
        "job_file": "random_basics\\jobs\\Random_UnitVector_Job.json",
        "graphspec_file": "random_basics\\graphspecs\\Random_UnitVector_GraphSpec.json"
      }
    ],
    "/Script/Engine.KismetMathLibrary:MakeRotator": [
      {
        "pack_name": "rotator_basics",
        "snippet_name": "Rotator_MakeBreak",
        "bpgen_function_name": "BPGen_Rotator_MakeBreak",
        "job_file": "rotator_basics\\jobs\\Rotator_MakeBreak_Job.json",
        "graphspec_file": "rotator_basics\\graphspecs\\Rotator_MakeBreak_GraphSpec.json"
      }
    ],
    "/Script/Engine.KismetMathLibrary:ComposeRotators": [
      {
        "pack_name": "rotator_basics",
        "snippet_name": "Rotator_Compose",
        "bpgen_function_name": "BPGen_Rotator_Compose",
        "job_file": "rotator_basics\\jobs\\Rotator_Compose_Job.json",
        "graphspec_file": "rotator_basics\\graphspecs\\Rotator_Compose_GraphSpec.json"
      }
    ],
    "/Script/Engine.GameplayStatics:CreateSaveGameObject": [
      {
        "pack_name": "savegame_basics",
        "snippet_name": "SaveGame_CreateObject",
        "bpgen_function_name": "BPGen_SaveGame_CreateObject",
        "job_file": "savegame_basics\\jobs\\SaveGame_CreateObject_Job.json",
        "graphspec_file": "savegame_basics\\graphspecs\\SaveGame_CreateObject_GraphSpec.json"
      }
    ],
    "/Script/Engine.GameplayStatics:SaveGameToSlot": [
      {
        "pack_name": "savegame_basics",
        "snippet_name": "SaveGame_SaveToSlot",
        "bpgen_function_name": "BPGen_SaveGame_SaveToSlot",
        "job_file": "savegame_basics\\jobs\\SaveGame_SaveToSlot_Job.json",
        "graphspec_file": "savegame_basics\\graphspecs\\SaveGame_SaveToSlot_GraphSpec.json"
      }
    ],
    "/Script/Engine.GameplayStatics:LoadGameFromSlot": [
      {
        "pack_name": "savegame_basics",
        "snippet_name": "SaveGame_LoadFromSlot",
        "bpgen_function_name": "BPGen_SaveGame_LoadFromSlot",
        "job_file": "savegame_basics\\jobs\\SaveGame_LoadFromSlot_Job.json",
        "graphspec_file": "savegame_basics\\graphspecs\\SaveGame_LoadFromSlot_GraphSpec.json"
      }
    ],
    "/Script/Engine.KismetStringLibrary:Concat_StrStr": [
      {
        "pack_name": "string_basics",
        "snippet_name": "String_Append",
        "bpgen_function_name": "BPGen_String_Append",
        "job_file": "string_basics\\jobs\\String_Append_Job.json",
        "graphspec_file": "string_basics\\graphspecs\\String_Append_GraphSpec.json"
      }
    ],
    "/Script/Engine.KismetStringLibrary:EqualEqual_StriStri": [
      {
        "pack_name": "string_basics",
        "snippet_name": "String_EqualIgnoreCase",
        "bpgen_function_name": "BPGen_String_EqualIgnoreCase",
        "job_file": "string_basics\\jobs\\String_EqualIgnoreCase_Job.json",
        "graphspec_file": "string_basics\\graphspecs\\String_EqualIgnoreCase_GraphSpec.json"
      }
    ],
    "/Script/Engine.KismetStringLibrary:Format": [
      {
        "pack_name": "string_basics",
        "snippet_name": "String_FormatNameValue",
        "bpgen_function_name": "BPGen_String_FormatNameValue",
        "job_file": "string_basics\\jobs\\String_FormatNameValue_Job.json",
        "graphspec_file": "string_basics\\graphspecs\\String_FormatNameValue_GraphSpec.json"
      }
    ],
    "NO_CALL_FUNCTION_NODE": [
      {
        "pack_name": "struct_basics",
        "snippet_name": "HitResult_Break",
        "bpgen_function_name": "BPGen_HitResult_Break",
        "job_file": "struct_basics\\jobs\\HitResult_Break_Job.json",
        "graphspec_file": "struct_basics\\graphspecs\\HitResult_Break_GraphSpec.json"
      }
    ],
    "/Script/Engine.KismetMathLibrary:MakeTransform": [
      {
        "pack_name": "struct_basics",
        "snippet_name": "Transform_MakeBreak",
        "bpgen_function_name": "BPGen_Transform_MakeBreak",
        "job_file": "struct_basics\\jobs\\Transform_MakeBreak_Job.json",
        "graphspec_file": "struct_basics\\graphspecs\\Transform_MakeBreak_GraphSpec.json"
      },
      {
        "pack_name": "transform_basics",
        "snippet_name": "Transform_MakeTransform",
        "bpgen_function_name": "BPGen_Transform_MakeTransform",
        "job_file": "transform_basics\\jobs\\Transform_MakeTransform_Job.json",
        "graphspec_file": "transform_basics\\graphspecs\\Transform_MakeTransform_GraphSpec.json"
      }
    ],
    "/Script/Engine.KismetSystemLibrary:K2_SetTimer": [
      {
        "pack_name": "timer_basics",
        "snippet_name": "Timer_SetTimerByFunctionName",
        "bpgen_function_name": "BPGen_Timer_SetTimerByFunctionName",
        "job_file": "timer_basics\\jobs\\Timer_SetTimerByFunctionName_Job.json",
        "graphspec_file": "timer_basics\\graphspecs\\Timer_SetTimerByFunctionName_GraphSpec.json"
      }
    ],
    "/Script/Engine.KismetSystemLibrary:K2_ClearTimer": [
      {
        "pack_name": "timer_basics",
        "snippet_name": "Timer_ClearTimerByFunctionName",
        "bpgen_function_name": "BPGen_Timer_ClearTimerByFunctionName",
        "job_file": "timer_basics\\jobs\\Timer_ClearTimerByFunctionName_Job.json",
        "graphspec_file": "timer_basics\\graphspecs\\Timer_ClearTimerByFunctionName_GraphSpec.json"
      }
    ],
    "/Script/Engine.KismetSystemLibrary:GetGameTimeInSeconds": [
      {
        "pack_name": "time_world_basics",
        "snippet_name": "Time_GetGameTimeInSeconds",
        "bpgen_function_name": "BPGen_Time_GetGameTimeInSeconds",
        "job_file": "time_world_basics\\jobs\\Time_GetGameTimeInSeconds_Job.json",
        "graphspec_file": "time_world_basics\\graphspecs\\Time_GetGameTimeInSeconds_GraphSpec.json"
      }
    ],
    "/Script/Engine.KismetSystemLibrary:GetRealTimeSeconds": [
      {
        "pack_name": "time_world_basics",
        "snippet_name": "Time_GetRealTimeSeconds",
        "bpgen_function_name": "BPGen_Time_GetRealTimeSeconds",
        "job_file": "time_world_basics\\jobs\\Time_GetRealTimeSeconds_Job.json",
        "graphspec_file": "time_world_basics\\graphspecs\\Time_GetRealTimeSeconds_GraphSpec.json"
      }
    ],
    "/Script/Engine.KismetSystemLibrary:GetUnpausedTimeSeconds": [
      {
        "pack_name": "time_world_basics",
        "snippet_name": "Time_GetUnpausedTimeSeconds",
        "bpgen_function_name": "BPGen_Time_GetUnpausedTimeSeconds",
        "job_file": "time_world_basics\\jobs\\Time_GetUnpausedTimeSeconds_Job.json",
        "graphspec_file": "time_world_basics\\graphspecs\\Time_GetUnpausedTimeSeconds_GraphSpec.json"
      }
    ],
    "/Script/Engine.KismetSystemLibrary:SphereTraceMulti": [
      {
        "pack_name": "trace_advanced",
        "snippet_name": "SphereTrace_Multi",
        "bpgen_function_name": "BPGen_Trace_SphereTraceMulti",
        "job_file": "trace_advanced\\jobs\\SphereTrace_Multi_Job.json",
        "graphspec_file": "trace_advanced\\graphspecs\\SphereTrace_Multi_GraphSpec.json"
      }
    ],
    "/Script/Engine.KismetSystemLibrary:CapsuleTraceSingle": [
      {
        "pack_name": "trace_advanced",
        "snippet_name": "CapsuleTrace_Single",
        "bpgen_function_name": "BPGen_Trace_CapsuleTraceSingle",
        "job_file": "trace_advanced\\jobs\\CapsuleTrace_Single_Job.json",
        "graphspec_file": "trace_advanced\\graphspecs\\CapsuleTrace_Single_GraphSpec.json"
      }
    ],
    "/Script/Engine.KismetSystemLibrary:LineTraceMulti": [
      {
        "pack_name": "trace_basics",
        "snippet_name": "Trace_LineMulti",
        "bpgen_function_name": "BPGen_Trace_LineMulti",
        "job_file": "trace_basics\\jobs\\Trace_LineMulti_Job.json",
        "graphspec_file": "trace_basics\\graphspecs\\Trace_LineMulti_GraphSpec.json"
      },
      {
        "pack_name": "trace_line_channel_basics",
        "snippet_name": "Trace_LineMulti",
        "bpgen_function_name": "BPGen_Trace_LineMulti",
        "job_file": "trace_line_channel_basics\\jobs\\Trace_LineMulti_Job.json",
        "graphspec_file": "trace_line_channel_basics\\graphspecs\\Trace_LineMulti_GraphSpec.json"
      }
    ],
    "/Script/Engine.KismetSystemLibrary:SphereTraceSingle": [
      {
        "pack_name": "trace_basics",
        "snippet_name": "Trace_SphereSingle",
        "bpgen_function_name": "BPGen_Trace_SphereSingle",
        "job_file": "trace_basics\\jobs\\Trace_SphereSingle_Job.json",
        "graphspec_file": "trace_basics\\graphspecs\\Trace_SphereSingle_GraphSpec.json"
      },
      {
        "pack_name": "trace_line_channel_basics",
        "snippet_name": "Trace_SphereSingle",
        "bpgen_function_name": "BPGen_Trace_SphereSingle",
        "job_file": "trace_line_channel_basics\\jobs\\Trace_SphereSingle_Job.json",
        "graphspec_file": "trace_line_channel_basics\\graphspecs\\Trace_SphereSingle_GraphSpec.json"
      }
    ],
    "/Script/Engine.KismetMathLibrary:TransformLocation": [
      {
        "pack_name": "transform_basics",
        "snippet_name": "Transform_TransformLocation",
        "bpgen_function_name": "BPGen_Transform_TransformLocation",
        "job_file": "transform_basics\\jobs\\Transform_TransformLocation_Job.json",
        "graphspec_file": "transform_basics\\graphspecs\\Transform_TransformLocation_GraphSpec.json"
      },
      {
        "pack_name": "vector_transform_basics",
        "snippet_name": "TransformLocation_Basic",
        "bpgen_function_name": "BPGen_TransformLocation",
        "job_file": "vector_transform_basics\\jobs\\TransformLocation_Basic_Job.json",
        "graphspec_file": "vector_transform_basics\\graphspecs\\TransformLocation_Basic_GraphSpec.json"
      }
    ],
    "/Script/Engine.KismetMathLibrary:InverseTransformLocation": [
      {
        "pack_name": "transform_basics",
        "snippet_name": "Transform_InverseTransformLocation",
        "bpgen_function_name": "BPGen_Transform_InverseTransformLocation",
        "job_file": "transform_basics\\jobs\\Transform_InverseTransformLocation_Job.json",
        "graphspec_file": "transform_basics\\graphspecs\\Transform_InverseTransformLocation_GraphSpec.json"
      },
      {
        "pack_name": "vector_transform_basics",
        "snippet_name": "InverseTransformLocation_Basic",
        "bpgen_function_name": "BPGen_InverseTransformLocation",
        "job_file": "vector_transform_basics\\jobs\\InverseTransformLocation_Basic_Job.json",
        "graphspec_file": "vector_transform_basics\\graphspecs\\InverseTransformLocation_Basic_GraphSpec.json"
      }
    ],
    "/Script/Engine.KismetMathLibrary:RotateVector": [
      {
        "pack_name": "transform_math_basics",
        "snippet_name": "Transform_RotateVector",
        "bpgen_function_name": "BPGen_Transform_RotateVector",
        "job_file": "transform_math_basics\\jobs\\Transform_RotateVector_Job.json",
        "graphspec_file": "transform_math_basics\\graphspecs\\Transform_RotateVector_GraphSpec.json"
      }
    ],
    "/Script/Engine.KismetMathLibrary:MakeVector": [
      {
        "pack_name": "vector_transform_basics",
        "snippet_name": "Vector_MakeBreak",
        "bpgen_function_name": "BPGen_Vector_MakeBreak",
        "job_file": "vector_transform_basics\\jobs\\Vector_MakeBreak_Job.json",
        "graphspec_file": "vector_transform_basics\\graphspecs\\Vector_MakeBreak_GraphSpec.json"
      }
    ],
    "/Script/UMG.UserWidget:CreateWidget": [
      {
        "pack_name": "widget_basics",
        "snippet_name": "Widget_CreateAndAddToViewport",
        "bpgen_function_name": "BPGen_Widget_CreateAndAddToViewport",
        "job_file": "widget_basics\\jobs\\Widget_CreateAndAddToViewport_Job.json",
        "graphspec_file": "widget_basics\\graphspecs\\Widget_CreateAndAddToViewport_GraphSpec.json"
      }
    ],
    "/Script/UMG.Widget:RemoveFromParent": [
      {
        "pack_name": "widget_basics",
        "snippet_name": "Widget_RemoveFromParent",
        "bpgen_function_name": "BPGen_Widget_RemoveFromParent",
        "job_file": "widget_basics\\jobs\\Widget_RemoveFromParent_Job.json",
        "graphspec_file": "widget_basics\\graphspecs\\Widget_RemoveFromParent_GraphSpec.json"
      }
    ],
    "/Script/UMG.Widget:SetIsEnabled": [
      {
        "pack_name": "widget_basics",
        "snippet_name": "Widget_SetIsEnabled",
        "bpgen_function_name": "BPGen_Widget_SetIsEnabled",
        "job_file": "widget_basics\\jobs\\Widget_SetIsEnabled_Job.json",
        "graphspec_file": "widget_basics\\graphspecs\\Widget_SetIsEnabled_GraphSpec.json"
      }
    ],
    "/Script/UMG.UserWidget:GetOwningPlayer": [
      {
        "pack_name": "widget_tree_access_basics",
        "snippet_name": "Widget_GetOwningPlayer",
        "bpgen_function_name": "BPGen_Widget_GetOwningPlayer",
        "job_file": "widget_tree_access_basics\\jobs\\Widget_GetOwningPlayer_Job.json",
        "graphspec_file": "widget_tree_access_basics\\graphspecs\\Widget_GetOwningPlayer_GraphSpec.json"
      }
    ],
    "/Script/UMG.UserWidget:GetWidgetFromName": [
      {
        "pack_name": "widget_tree_access_basics",
        "snippet_name": "Widget_GetWidgetFromName",
        "bpgen_function_name": "BPGen_Widget_GetWidgetFromName",
        "job_file": "widget_tree_access_basics\\jobs\\Widget_GetWidgetFromName_Job.json",
        "graphspec_file": "widget_tree_access_basics\\graphspecs\\Widget_GetWidgetFromName_GraphSpec.json"
      }
    ],
    "/Script/UMG.UserWidget:GetRootWidget": [
      {
        "pack_name": "widget_tree_access_basics",
        "snippet_name": "Widget_GetRootWidget",
        "bpgen_function_name": "BPGen_Widget_GetRootWidget",
        "job_file": "widget_tree_access_basics\\jobs\\Widget_GetRootWidget_Job.json",
        "graphspec_file": "widget_tree_access_basics\\graphspecs\\Widget_GetRootWidget_GraphSpec.json"
      }
    ]
  },
  "duplicates": {
    "/Script/Engine.KismetSystemLibrary:PrintString": [
      {
        "pack_name": "array_basics",
        "snippet_name": "IntArray_ForEach_Print",
        "bpgen_function_name": "BPGen_Array_ForEachPrint",
        "job_file": "array_basics\\jobs\\IntArray_ForEach_Print_Job.json",
        "graphspec_file": "array_basics\\graphspecs\\IntArray_ForEach_Print_GraphSpec.json"
      },
      {
        "pack_name": "common_basics",
        "snippet_name": "PrintString_HelloWorld",
        "bpgen_function_name": "BPGen_HelloWorld",
        "job_file": "common_basics\\jobs\\PrintString_HelloWorld_Job.json",
        "graphspec_file": "common_basics\\graphspecs\\PrintString_HelloWorld_GraphSpec.json"
      },
      {
        "pack_name": "common_basics",
        "snippet_name": "Branch_Boilerplate",
        "bpgen_function_name": "BPGen_BranchBoilerplate",
        "job_file": "common_basics\\jobs\\Branch_Boilerplate_Job.json",
        "graphspec_file": "common_basics\\graphspecs\\Branch_Boilerplate_GraphSpec.json"
      },
      {
        "pack_name": "debug_basics",
        "snippet_name": "Debug_PrintScreenLog",
        "bpgen_function_name": "BPGen_Debug_PrintScreenLog",
        "job_file": "debug_basics\\jobs\\Debug_PrintScreenLog_Job.json",
        "graphspec_file": "debug_basics\\graphspecs\\Debug_PrintScreenLog_GraphSpec.json"
      },
      {
        "pack_name": "event_basics",
        "snippet_name": "CustomEvent_Simple",
        "bpgen_function_name": "BPGen_CustomEvent_Simple",
        "job_file": "event_basics\\jobs\\CustomEvent_Simple_Job.json",
        "graphspec_file": "event_basics\\graphspecs\\CustomEvent_Simple_GraphSpec.json"
      },
      {
        "pack_name": "flow_advanced",
        "snippet_name": "Flow_DoOnceWithReset",
        "bpgen_function_name": "BPGen_Flow_DoOnceWithReset",
        "job_file": "flow_advanced\\jobs\\Flow_DoOnceWithReset_Job.json",
        "graphspec_file": "flow_advanced\\graphspecs\\Flow_DoOnceWithReset_GraphSpec.json"
      },
      {
        "pack_name": "flow_advanced",
        "snippet_name": "Flow_Gate_OpenClose",
        "bpgen_function_name": "BPGen_Flow_Gate_OpenClose",
        "job_file": "flow_advanced\\jobs\\Flow_Gate_OpenClose_Job.json",
        "graphspec_file": "flow_advanced\\graphspecs\\Flow_Gate_OpenClose_GraphSpec.json"
      },
      {
        "pack_name": "flow_advanced",
        "snippet_name": "Flow_MultiGate_Triple",
        "bpgen_function_name": "BPGen_Flow_MultiGate_Triple",
        "job_file": "flow_advanced\\jobs\\Flow_MultiGate_Triple_Job.json",
        "graphspec_file": "flow_advanced\\graphspecs\\Flow_MultiGate_Triple_GraphSpec.json"
      },
      {
        "pack_name": "flow_basics",
        "snippet_name": "Branch_BoolInput",
        "bpgen_function_name": "BPGen_Flow_Branch",
        "job_file": "flow_basics\\jobs\\Branch_BoolInput_Job.json",
        "graphspec_file": "flow_basics\\graphspecs\\Branch_BoolInput_GraphSpec.json"
      },
      {
        "pack_name": "flow_basics",
        "snippet_name": "ForLoop_Basic",
        "bpgen_function_name": "BPGen_Flow_ForLoop",
        "job_file": "flow_basics\\jobs\\ForLoop_Basic_Job.json",
        "graphspec_file": "flow_basics\\graphspecs\\ForLoop_Basic_GraphSpec.json"
      },
      {
        "pack_name": "flow_basics",
        "snippet_name": "Sequence_Triple",
        "bpgen_function_name": "BPGen_Flow_Sequence",
        "job_file": "flow_basics\\jobs\\Sequence_Triple_Job.json",
        "graphspec_file": "flow_basics\\graphspecs\\Sequence_Triple_GraphSpec.json"
      }
    ],
    "/Script/Engine.KismetMathLibrary:BooleanAND": [
      {
        "pack_name": "bool_logic_basics",
        "snippet_name": "Bool_AndOr",
        "bpgen_function_name": "BPGen_Bool_AndOr",
        "job_file": "bool_logic_basics\\jobs\\Bool_AndOr_Job.json",
        "graphspec_file": "bool_logic_basics\\graphspecs\\Bool_AndOr_GraphSpec.json"
      },
      {
        "pack_name": "bool_logic_basics",
        "snippet_name": "Branch_ComplexCondition",
        "bpgen_function_name": "BPGen_Branch_ComplexCondition",
        "job_file": "bool_logic_basics\\jobs\\Branch_ComplexCondition_Job.json",
        "graphspec_file": "bool_logic_basics\\graphspecs\\Branch_ComplexCondition_GraphSpec.json"
      }
    ],
    "/Script/Engine.KismetSystemLibrary:LineTraceSingle": [
      {
        "pack_name": "common_basics",
        "snippet_name": "SimpleTrace_LineTraceSingle",
        "bpgen_function_name": "BPGen_SimpleTrace",
        "job_file": "common_basics\\jobs\\SimpleTrace_LineTraceSingle_Job.json",
        "graphspec_file": "common_basics\\graphspecs\\SimpleTrace_LineTraceSingle_GraphSpec.json"
      },
      {
        "pack_name": "trace_advanced",
        "snippet_name": "LineTrace_ByChannel_Advanced",
        "bpgen_function_name": "BPGen_Trace_LineTraceAdv",
        "job_file": "trace_advanced\\jobs\\LineTrace_ByChannel_Advanced_Job.json",
        "graphspec_file": "trace_advanced\\graphspecs\\LineTrace_ByChannel_Advanced_GraphSpec.json"
      },
      {
        "pack_name": "trace_basics",
        "snippet_name": "Trace_LineSingle",
        "bpgen_function_name": "BPGen_Trace_LineSingle",
        "job_file": "trace_basics\\jobs\\Trace_LineSingle_Job.json",
        "graphspec_file": "trace_basics\\graphspecs\\Trace_LineSingle_GraphSpec.json"
      },
      {
        "pack_name": "trace_line_channel_basics",
        "snippet_name": "Trace_LineSingle",
        "bpgen_function_name": "BPGen_Trace_LineSingle",
        "job_file": "trace_line_channel_basics\\jobs\\Trace_LineSingle_Job.json",
        "graphspec_file": "trace_line_channel_basics\\graphspecs\\Trace_LineSingle_GraphSpec.json"
      }
    ],
    "/Script/Engine.CurveFloat:GetFloatValue": [
      {
        "pack_name": "curve_basics",
        "snippet_name": "CurveFloat_Eval",
        "bpgen_function_name": "BPGen_CurveFloat_Eval",
        "job_file": "curve_basics\\jobs\\CurveFloat_Eval_Job.json",
        "graphspec_file": "curve_basics\\graphspecs\\CurveFloat_Eval_GraphSpec.json"
      },
      {
        "pack_name": "curve_eval_basics",
        "snippet_name": "CurveFloat_GetValue",
        "bpgen_function_name": "BPGen_CurveFloat_GetValue",
        "job_file": "curve_eval_basics\\jobs\\CurveFloat_GetValue_Job.json",
        "graphspec_file": "curve_eval_basics\\graphspecs\\CurveFloat_GetValue_GraphSpec.json"
      }
    ],
    "/Script/Engine.CurveVector:GetVectorValue": [
      {
        "pack_name": "curve_basics",
        "snippet_name": "CurveVector_Eval",
        "bpgen_function_name": "BPGen_CurveVector_Eval",
        "job_file": "curve_basics\\jobs\\CurveVector_Eval_Job.json",
        "graphspec_file": "curve_basics\\graphspecs\\CurveVector_Eval_GraphSpec.json"
      },
      {
        "pack_name": "curve_eval_basics",
        "snippet_name": "CurveVector_GetValue",
        "bpgen_function_name": "BPGen_CurveVector_GetValue",
        "job_file": "curve_eval_basics\\jobs\\CurveVector_GetValue_Job.json",
        "graphspec_file": "curve_eval_basics\\graphspecs\\CurveVector_GetValue_GraphSpec.json"
      }
    ],
    "/Script/Engine.KismetDataTableLibrary:GetDataTableRow": [
      {
        "pack_name": "datatable_query_basics",
        "snippet_name": "DataTable_GetRow",
        "bpgen_function_name": "BPGen_DataTable_GetRow",
        "job_file": "datatable_query_basics\\jobs\\DataTable_GetRow_Job.json",
        "graphspec_file": "datatable_query_basics\\graphspecs\\DataTable_GetRow_GraphSpec.json"
      },
      {
        "pack_name": "datatable_query_basics",
        "snippet_name": "DataTable_RowExists",
        "bpgen_function_name": "BPGen_DataTable_RowExists",
        "job_file": "datatable_query_basics\\jobs\\DataTable_RowExists_Job.json",
        "graphspec_file": "datatable_query_basics\\graphspecs\\DataTable_RowExists_GraphSpec.json"
      }
    ],
    "/Script/Engine.KismetMathLibrary:Multiply_FloatFloat": [
      {
        "pack_name": "input_basics",
        "snippet_name": "Input_ScaleAxis",
        "bpgen_function_name": "BPGen_Input_ScaleAxis",
        "job_file": "input_basics\\jobs\\Input_ScaleAxis_Job.json",
        "graphspec_file": "input_basics\\graphspecs\\Input_ScaleAxis_GraphSpec.json"
      },
      {
        "pack_name": "math_basics",
        "snippet_name": "Float_MultiplyDivide",
        "bpgen_function_name": "BPGen_Math_FloatMulDiv",
        "job_file": "math_basics\\jobs\\Float_MultiplyDivide_Job.json",
        "graphspec_file": "math_basics\\graphspecs\\Float_MultiplyDivide_GraphSpec.json"
      }
    ],
    "/Script/Engine.KismetMathLibrary:FInterpTo": [
      {
        "pack_name": "interp_basics",
        "snippet_name": "Float_FInterpTo",
        "bpgen_function_name": "BPGen_Float_FInterpTo",
        "job_file": "interp_basics\\jobs\\Float_FInterpTo_Job.json",
        "graphspec_file": "interp_basics\\graphspecs\\Float_FInterpTo_GraphSpec.json"
      },
      {
        "pack_name": "interp_helpers_basics",
        "snippet_name": "Interp_FInterpTo",
        "bpgen_function_name": "BPGen_Interp_FInterpTo",
        "job_file": "interp_helpers_basics\\jobs\\Interp_FInterpTo_Job.json",
        "graphspec_file": "interp_helpers_basics\\graphspecs\\Interp_FInterpTo_GraphSpec.json"
      }
    ],
    "/Script/Engine.KismetMathLibrary:VInterpTo": [
      {
        "pack_name": "interp_basics",
        "snippet_name": "Vector_VInterpTo",
        "bpgen_function_name": "BPGen_Vector_VInterpTo",
        "job_file": "interp_basics\\jobs\\Vector_VInterpTo_Job.json",
        "graphspec_file": "interp_basics\\graphspecs\\Vector_VInterpTo_GraphSpec.json"
      },
      {
        "pack_name": "interp_helpers_basics",
        "snippet_name": "Interp_VInterpTo",
        "bpgen_function_name": "BPGen_Interp_VInterpTo",
        "job_file": "interp_helpers_basics\\jobs\\Interp_VInterpTo_Job.json",
        "graphspec_file": "interp_helpers_basics\\graphspecs\\Interp_VInterpTo_GraphSpec.json"
      }
    ],
    "/Script/Engine.KismetMathLibrary:RInterpTo": [
      {
        "pack_name": "interp_helpers_basics",
        "snippet_name": "Interp_RInterpTo",
        "bpgen_function_name": "BPGen_Interp_RInterpTo",
        "job_file": "interp_helpers_basics\\jobs\\Interp_RInterpTo_Job.json",
        "graphspec_file": "interp_helpers_basics\\graphspecs\\Interp_RInterpTo_GraphSpec.json"
      },
      {
        "pack_name": "rotator_basics",
        "snippet_name": "Rotator_RInterpTo",
        "bpgen_function_name": "BPGen_Rotator_RInterpTo",
        "job_file": "rotator_basics\\jobs\\Rotator_RInterpTo_Job.json",
        "graphspec_file": "rotator_basics\\graphspecs\\Rotator_RInterpTo_GraphSpec.json"
      }
    ],
    "/Script/Engine.KismetMathLibrary:MakeTransform": [
      {
        "pack_name": "struct_basics",
        "snippet_name": "Transform_MakeBreak",
        "bpgen_function_name": "BPGen_Transform_MakeBreak",
        "job_file": "struct_basics\\jobs\\Transform_MakeBreak_Job.json",
        "graphspec_file": "struct_basics\\graphspecs\\Transform_MakeBreak_GraphSpec.json"
      },
      {
        "pack_name": "transform_basics",
        "snippet_name": "Transform_MakeTransform",
        "bpgen_function_name": "BPGen_Transform_MakeTransform",
        "job_file": "transform_basics\\jobs\\Transform_MakeTransform_Job.json",
        "graphspec_file": "transform_basics\\graphspecs\\Transform_MakeTransform_GraphSpec.json"
      }
    ],
    "/Script/Engine.KismetSystemLibrary:LineTraceMulti": [
      {
        "pack_name": "trace_basics",
        "snippet_name": "Trace_LineMulti",
        "bpgen_function_name": "BPGen_Trace_LineMulti",
        "job_file": "trace_basics\\jobs\\Trace_LineMulti_Job.json",
        "graphspec_file": "trace_basics\\graphspecs\\Trace_LineMulti_GraphSpec.json"
      },
      {
        "pack_name": "trace_line_channel_basics",
        "snippet_name": "Trace_LineMulti",
        "bpgen_function_name": "BPGen_Trace_LineMulti",
        "job_file": "trace_line_channel_basics\\jobs\\Trace_LineMulti_Job.json",
        "graphspec_file": "trace_line_channel_basics\\graphspecs\\Trace_LineMulti_GraphSpec.json"
      }
    ],
    "/Script/Engine.KismetSystemLibrary:SphereTraceSingle": [
      {
        "pack_name": "trace_basics",
        "snippet_name": "Trace_SphereSingle",
        "bpgen_function_name": "BPGen_Trace_SphereSingle",
        "job_file": "trace_basics\\jobs\\Trace_SphereSingle_Job.json",
        "graphspec_file": "trace_basics\\graphspecs\\Trace_SphereSingle_GraphSpec.json"
      },
      {
        "pack_name": "trace_line_channel_basics",
        "snippet_name": "Trace_SphereSingle",
        "bpgen_function_name": "BPGen_Trace_SphereSingle",
        "job_file": "trace_line_channel_basics\\jobs\\Trace_SphereSingle_Job.json",
        "graphspec_file": "trace_line_channel_basics\\graphspecs\\Trace_SphereSingle_GraphSpec.json"
      }
    ],
    "/Script/Engine.KismetMathLibrary:TransformLocation": [
      {
        "pack_name": "transform_basics",
        "snippet_name": "Transform_TransformLocation",
        "bpgen_function_name": "BPGen_Transform_TransformLocation",
        "job_file": "transform_basics\\jobs\\Transform_TransformLocation_Job.json",
        "graphspec_file": "transform_basics\\graphspecs\\Transform_TransformLocation_GraphSpec.json"
      },
      {
        "pack_name": "vector_transform_basics",
        "snippet_name": "TransformLocation_Basic",
        "bpgen_function_name": "BPGen_TransformLocation",
        "job_file": "vector_transform_basics\\jobs\\TransformLocation_Basic_Job.json",
        "graphspec_file": "vector_transform_basics\\graphspecs\\TransformLocation_Basic_GraphSpec.json"
      }
    ],
    "/Script/Engine.KismetMathLibrary:InverseTransformLocation": [
      {
        "pack_name": "transform_basics",
        "snippet_name": "Transform_InverseTransformLocation",
        "bpgen_function_name": "BPGen_Transform_InverseTransformLocation",
        "job_file": "transform_basics\\jobs\\Transform_InverseTransformLocation_Job.json",
        "graphspec_file": "transform_basics\\graphspecs\\Transform_InverseTransformLocation_GraphSpec.json"
      },
      {
        "pack_name": "vector_transform_basics",
        "snippet_name": "InverseTransformLocation_Basic",
        "bpgen_function_name": "BPGen_InverseTransformLocation",
        "job_file": "vector_transform_basics\\jobs\\InverseTransformLocation_Basic_Job.json",
        "graphspec_file": "vector_transform_basics\\graphspecs\\InverseTransformLocation_Basic_GraphSpec.json"
      }
    ]
  }
}