{
  "Function": {
    "TargetBlueprintPath": "/Game/DevTools/BP_BPGen_Level_GetStreamingLevel_Ref.BP_BPGen_Level_GetStreamingLevel_Ref",
    "FunctionName": "BPGen_Level_GetStreamingLevel_Ref",
    "Inputs": [
      {
        "Name": "WorldContextObject",
        "Category": "object",
        "SubCategory": "",
        "SubObjectPath": "Class'/Script/CoreUObject.Object'",
        "ContainerType": "None",
        "Direction": "Input",
        "DefaultValue": "",
        "Members": []
      },
      {
        "Name": "LevelName",
        "Category": "name",
        "SubCategory": "",
        "SubObjectPath": "",
        "ContainerType": "None",
        "Direction": "Input",
        "DefaultValue": "",
        "Members": []
      }
    ],
    "Outputs": [
      {
        "Name": "StreamingLevel",
        "Category": "object",
        "SubCategory": "",
        "SubObjectPath": "Class'/Script/Engine.LevelStreaming'",
        "ContainerType": "None",
        "Direction": "Output",
        "DefaultValue": "",
        "Members": []
      }
    ]
  },
  "StructsToCreate": [],
  "EnumsToCreate": []
}