{
	"floatCurves": [
		{
			"keys": [
				{
					"interpMode": "RCIM_Cubic",
					"tangentMode": "RCTM_User",
					"tangentWeightMode": "RCTWM_WeightedNone",
					"time": 0.27358558773994446,
					"value": 0.46875,
					"arriveTangent": 0,
					"arriveTangentWeight": 0,
					"leaveTangent": 0,
					"leaveTangentWeight": 0.033997289836406708
				},
				{
					"interpMode": "RCIM_Cubic",
					"tangentMode": "RCTM_User",
					"tangentWeightMode": "RCTWM_WeightedNone",
					"time": 0.3934532105922699,
					"value": 0.4583333432674408,
					"arriveTangent": 0,
					"arriveTangentWeight": 0.064135663211345673,
					"leaveTangent": 0,
					"leaveTangentWeight": 0.038072206079959869
				},
				{
					"interpMode": "RCIM_Cubic",
					"tangentMode": "RCTM_Auto",
					"tangentWeightMode": "RCTWM_WeightedNone",
					"time": 0.4605444073677063,
					"value": 0.4739583432674408,
					"arriveTangent": 3.0941026210784912,
					"arriveTangentWeight": 0,
					"leaveTangent": 3.0941026210784912,
					"leaveTangentWeight": 0
				},
				{
					"interpMode": "RCIM_Cubic",
					"tangentMode": "RCTM_Auto",
					"tangentWeightMode": "RCTWM_WeightedNone",
					"time": 0.5,
					"value": 0.78800004720687866,
					"arriveTangent": 19.372182846069336,
					"arriveTangentWeight": 0,
					"leaveTangent": 19.372182846069336,
					"leaveTangentWeight": 0
				},
				{
					"interpMode": "RCIM_Cubic",
					"tangentMode": "RCTM_Auto",
					"tangentWeightMode": "RCTWM_WeightedNone",
					"time": 0.52020478248596191,
					"value": 1.2000000476837158,
					"arriveTangent": 23.322500228881836,
					"arriveTangentWeight": 0,
					"leaveTangent": 23.322500228881836,
					"leaveTangentWeight": 0
				},
				{
					"interpMode": "RCIM_Cubic",
					"tangentMode": "RCTM_Auto",
					"tangentWeightMode": "RCTWM_WeightedNone",
					"time": 0.59093970060348511,
					"value": 3,
					"arriveTangent": 23.322500228881836,
					"arriveTangentWeight": 0,
					"leaveTangent": 23.322500228881836,
					"leaveTangentWeight": 0
				},
				{
					"interpMode": "RCIM_Cubic",
					"tangentMode": "RCTM_Auto",
					"tangentWeightMode": "RCTWM_WeightedNone",
					"time": 0.69999998807907104,
					"value": 5.4524998664855957,
					"arriveTangent": 17.097936630249023,
					"arriveTangentWeight": 0,
					"leaveTangent": 17.097936630249023,
					"leaveTangentWeight": 0
				},
				{
					"interpMode": "RCIM_Cubic",
					"tangentMode": "RCTM_Auto",
					"tangentWeightMode": "RCTWM_WeightedNone",
					"time": 0.80000001192092896,
					"value": 6.5745000839233398,
					"arriveTangent": 14.59890079498291,
					"arriveTangentWeight": 0,
					"leaveTangent": 14.59890079498291,
					"leaveTangentWeight": 0
				},
				{
					"interpMode": "RCIM_Cubic",
					"tangentMode": "RCTM_Auto",
					"tangentWeightMode": "RCTWM_WeightedNone",
					"time": 0.90049457550048828,
					"value": 8.3795003890991211,
					"arriveTangent": 21.650949478149414,
					"arriveTangentWeight": 0,
					"leaveTangent": 21.650949478149414,
					"leaveTangentWeight": 0
				},
				{
					"interpMode": "RCIM_Linear",
					"tangentMode": "RCTM_Auto",
					"tangentWeightMode": "RCTWM_WeightedNone",
					"time": 0.99652719497680664,
					"value": 10.829500198364258,
					"arriveTangent": 0,
					"arriveTangentWeight": 0,
					"leaveTangent": 0,
					"leaveTangentWeight": 0
				}
			],
			"defaultValue": 3.4028234663852886e+38,
			"preInfinityExtrap": "RCCE_Constant",
			"postInfinityExtrap": "RCCE_Constant"
		},
		{
			"keys": [
				{
					"interpMode": "RCIM_Cubic",
					"tangentMode": "RCTM_User",
					"tangentWeightMode": "RCTWM_WeightedNone",
					"time": 0.27358558773994446,
					"value": 0.2197265625,
					"arriveTangent": 0,
					"arriveTangentWeight": 0,
					"leaveTangent": 0,
					"leaveTangentWeight": 0.033997289836406708
				},
				{
					"interpMode": "RCIM_Cubic",
					"tangentMode": "RCTM_User",
					"tangentWeightMode": "RCTWM_WeightedNone",
					"time": 0.3934532105922699,
					"value": 0.193359375,
					"arriveTangent": 0,
					"arriveTangentWeight": 0.041499011218547821,
					"leaveTangent": 0,
					"leaveTangentWeight": 0.024634640663862228
				},
				{
					"interpMode": "RCIM_Cubic",
					"tangentMode": "RCTM_Auto",
					"tangentWeightMode": "RCTWM_WeightedNone",
					"time": 0.4605444073677063,
					"value": 0.30527913570404053,
					"arriveTangent": 2.2036073207855225,
					"arriveTangentWeight": 0,
					"leaveTangent": 2.2036073207855225,
					"leaveTangentWeight": 0
				},
				{
					"interpMode": "RCIM_Cubic",
					"tangentMode": "RCTM_Auto",
					"tangentWeightMode": "RCTWM_WeightedNone",
					"time": 0.5,
					"value": 0.42814666032791138,
					"arriveTangent": 15.717052459716797,
					"arriveTangentWeight": 0,
					"leaveTangent": 15.717052459716797,
					"leaveTangentWeight": 0
				},
				{
					"interpMode": "RCIM_Cubic",
					"tangentMode": "RCTM_Auto",
					"tangentWeightMode": "RCTWM_WeightedNone",
					"time": 0.52020478248596191,
					"value": 0.777260422706604,
					"arriveTangent": 17.346765518188477,
					"arriveTangentWeight": 0,
					"leaveTangent": 17.346765518188477,
					"leaveTangentWeight": 0
				},
				{
					"interpMode": "RCIM_Cubic",
					"tangentMode": "RCTM_Auto",
					"tangentWeightMode": "RCTWM_WeightedNone",
					"time": 0.59093970060348511,
					"value": 2.3547086715698242,
					"arriveTangent": 17.346765518188477,
					"arriveTangentWeight": 0,
					"leaveTangent": 17.346765518188477,
					"leaveTangentWeight": 0
				},
				{
					"interpMode": "RCIM_Cubic",
					"tangentMode": "RCTM_Auto",
					"tangentWeightMode": "RCTWM_WeightedNone",
					"time": 0.69999998807907104,
					"value": 3.8974995613098145,
					"arriveTangent": 13.602734565734863,
					"arriveTangentWeight": 0,
					"leaveTangent": 13.602734565734863,
					"leaveTangentWeight": 0
				},
				{
					"interpMode": "RCIM_Cubic",
					"tangentMode": "RCTM_Auto",
					"tangentWeightMode": "RCTWM_WeightedNone",
					"time": 0.80000001192092896,
					"value": 5.1985006332397461,
					"arriveTangent": 16.601446151733398,
					"arriveTangentWeight": 0,
					"leaveTangent": 16.601446151733398,
					"leaveTangentWeight": 0
				},
				{
					"interpMode": "RCIM_Cubic",
					"tangentMode": "RCTM_Auto",
					"tangentWeightMode": "RCTWM_WeightedNone",
					"time": 0.90049457550048828,
					"value": 7.2259998321533203,
					"arriveTangent": 24.357952117919922,
					"arriveTangentWeight": 0,
					"leaveTangent": 24.357952117919922,
					"leaveTangentWeight": 0
				},
				{
					"interpMode": "RCIM_Linear",
					"tangentMode": "RCTM_Auto",
					"tangentWeightMode": "RCTWM_WeightedNone",
					"time": 0.99652719497680664,
					"value": 9.9855003356933594,
					"arriveTangent": 0,
					"arriveTangentWeight": 0,
					"leaveTangent": 0,
					"leaveTangentWeight": 0
				}
			],
			"defaultValue": 3.4028234663852886e+38,
			"preInfinityExtrap": "RCCE_Constant",
			"postInfinityExtrap": "RCCE_Constant"
		},
		{
			"keys": [
				{
					"interpMode": "RCIM_Cubic",
					"tangentMode": "RCTM_User",
					"tangentWeightMode": "RCTWM_WeightedNone",
					"time": 0.27358558773994446,
					"value": 0.230528324842453,
					"arriveTangent": 0,
					"arriveTangentWeight": 0,
					"leaveTangent": 0,
					"leaveTangentWeight": 0.033997289836406708
				},
				{
					"interpMode": "RCIM_Cubic",
					"tangentMode": "RCTM_User",
					"tangentWeightMode": "RCTWM_WeightedNone",
					"time": 0.3934532105922699,
					"value": 0.21329365670681,
					"arriveTangent": 0,
					"arriveTangentWeight": 0.038528352975845337,
					"leaveTangent": 0,
					"leaveTangentWeight": 0.022871199995279312
				},
				{
					"interpMode": "RCIM_Cubic",
					"tangentMode": "RCTM_Auto",
					"tangentWeightMode": "RCTWM_WeightedNone",
					"time": 0.4605444073677063,
					"value": 0.2740071713924408,
					"arriveTangent": 1.3410289287567139,
					"arriveTangentWeight": 0,
					"leaveTangent": 1.3410289287567139,
					"leaveTangentWeight": 0
				},
				{
					"interpMode": "RCIM_Cubic",
					"tangentMode": "RCTM_Auto",
					"tangentWeightMode": "RCTWM_WeightedNone",
					"time": 0.5,
					"value": 0.3561759889125824,
					"arriveTangent": 11.196666717529297,
					"arriveTangentWeight": 0,
					"leaveTangent": 11.196666717529297,
					"leaveTangentWeight": 0
				},
				{
					"interpMode": "RCIM_Cubic",
					"tangentMode": "RCTM_Auto",
					"tangentWeightMode": "RCTWM_WeightedNone",
					"time": 0.52020478248596191,
					"value": 0.63839995861053467,
					"arriveTangent": 9.5116195678710938,
					"arriveTangentWeight": 0,
					"leaveTangent": 9.5116195678710938,
					"leaveTangentWeight": 0
				},
				{
					"interpMode": "RCIM_Cubic",
					"tangentMode": "RCTM_Auto",
					"tangentWeightMode": "RCTWM_WeightedNone",
					"time": 0.59093970060348511,
					"value": 1.7339998483657837,
					"arriveTangent": 9.5116195678710938,
					"arriveTangentWeight": 0,
					"leaveTangent": 9.5116195678710938,
					"leaveTangentWeight": 0
				},
				{
					"interpMode": "RCIM_Cubic",
					"tangentMode": "RCTM_Auto",
					"tangentWeightMode": "RCTWM_WeightedNone",
					"time": 0.69999998807907104,
					"value": 2.2584998607635498,
					"arriveTangent": 7.9115934371948242,
					"arriveTangentWeight": 0,
					"leaveTangent": 7.9115934371948242,
					"leaveTangentWeight": 0
				},
				{
					"interpMode": "RCIM_Cubic",
					"tangentMode": "RCTM_Auto",
					"tangentWeightMode": "RCTWM_WeightedNone",
					"time": 0.80000001192092896,
					"value": 3.3880000114440918,
					"arriveTangent": 15.955546379089355,
					"arriveTangentWeight": 0,
					"leaveTangent": 15.955546379089355,
					"leaveTangentWeight": 0
				},
				{
					"interpMode": "RCIM_Cubic",
					"tangentMode": "RCTM_Auto",
					"tangentWeightMode": "RCTWM_WeightedNone",
					"time": 0.90049457550048828,
					"value": 5.4575004577636719,
					"arriveTangent": 25.001632690429688,
					"arriveTangentWeight": 0,
					"leaveTangent": 25.001632690429688,
					"leaveTangentWeight": 0
				},
				{
					"interpMode": "RCIM_Linear",
					"tangentMode": "RCTM_Auto",
					"tangentWeightMode": "RCTWM_WeightedNone",
					"time": 0.99652719497680664,
					"value": 8.3015003204345703,
					"arriveTangent": 0,
					"arriveTangentWeight": 0,
					"leaveTangent": 0,
					"leaveTangentWeight": 0
				}
			],
			"defaultValue": 3.4028234663852886e+38,
			"preInfinityExtrap": "RCCE_Constant",
			"postInfinityExtrap": "RCCE_Constant"
		},
		{
			"keys": [
				{
					"interpMode": "RCIM_Cubic",
					"tangentMode": "RCTM_User",
					"tangentWeightMode": "RCTWM_WeightedBoth",
					"time": 0.49545803666114807,
					"value": 1,
					"arriveTangent": 24.680561065673828,
					"arriveTangentWeight": 1.0164186954498291,
					"leaveTangent": 24.680561065673828,
					"leaveTangentWeight": 1.0164186954498291
				}
			],
			"defaultValue": 3.4028234663852886e+38,
			"preInfinityExtrap": "RCCE_Constant",
			"postInfinityExtrap": "RCCE_Constant"
		}
	],
	"adjustHue": 0,
	"adjustSaturation": 1,
	"adjustBrightness": 1,
	"adjustBrightnessCurve": 1,
	"adjustVibrance": 0,
	"adjustMinAlpha": 0,
	"adjustMaxAlpha": 1,
	"assetImportData":
	{
		"_ClassName": "/Script/Engine.AssetImportData",
		"sourceData":
		{
		}
	}
}