{
	"winter Average High Temp (C)": 26,
	"winter Average Low Temp (C)": 19,
	"spring Average High Temp (C)": 25,
	"spring Average Low Temp (C)": 19,
	"summer Average High Temp (C)": 30,
	"summer Average Low Temp (C)": 25,
	"autumn Average High Temp (C)": 31,
	"autumn Average Low Temp (C)": 25,
	"winter Cloudy Percentage": 45,
	"spring Cloudy Percentage": 34,
	"summer Cloudy Percentage": 57,
	"autumn Cloudy Percentage": 64,
	"winter Rainfall (mm)": 5.2999999999999998,
	"spring Rainfall (mm)": 0.69999999999999996,
	"summer Rainfall (mm)": 45.700000000000003,
	"autumn Rainfall (mm)": 28.399999999999999,
	"winter Snowfall (mm)": 0,
	"spring Snowfall (mm)": 0,
	"summer Snowfall (mm)": 0,
	"autumn Snowfall (mm)": 0,
	"dust/Sand Present": 0.5,
	"data Source": "Dakar, Senegal\r\nhttps://weatherspark.com/y/31520/Average-Weather-in-Dakar-Senegal-Year-Round",
	"assetBundleData": "",
	"nativeClass": "/Script/Engine.BlueprintGeneratedClass'/Game/SOTS/ThirdParty/Systems/UltraDynamicSky/Blueprints/Weather_Effects/System/UDS_Climate_Preset.UDS_Climate_Preset_C'"
}