{
	"winter Average High Temp (C)": 6,
	"winter Average Low Temp (C)": 0,
	"spring Average High Temp (C)": 18,
	"spring Average Low Temp (C)": 9,
	"summer Average High Temp (C)": 30,
	"summer Average Low Temp (C)": 19,
	"autumn Average High Temp (C)": 19,
	"autumn Average Low Temp (C)": 11,
	"winter Cloudy Percentage": 51,
	"spring Cloudy Percentage": 48,
	"summer Cloudy Percentage": 22,
	"autumn Cloudy Percentage": 46,
	"winter Rainfall (mm)": 28.600000000000001,
	"spring Rainfall (mm)": 47.600000000000001,
	"summer Rainfall (mm)": 31.600000000000001,
	"autumn Rainfall (mm)": 71.599999999999994,
	"winter Snowfall (mm)": 41.799999999999997,
	"spring Snowfall (mm)": 1.6000000000000001,
	"summer Snowfall (mm)": 0,
	"autumn Snowfall (mm)": 1.3999999999999999,
	"dust/Sand Present": 0,
	"data Source": "Bologna, Italy\r\nhttps://weatherspark.com/y/69251/Average-Weather-in-Bologna-Italy-Year-Round",
	"assetBundleData": "",
	"nativeClass": "/Script/Engine.BlueprintGeneratedClass'/Game/SOTS/ThirdParty/Systems/UltraDynamicSky/Blueprints/Weather_Effects/System/UDS_Climate_Preset.UDS_Climate_Preset_C'"
}